terminalprint/__init__.py
terminalprint/tprint.py
terminalprint-0.0.5.dist-info/LICENSE
terminalprint-0.0.5.dist-info/METADATA
terminalprint-0.0.5.dist-info/WHEEL
terminalprint-0.0.5.dist-info/top_level.txt
terminalprint-0.0.5.dist-info/RECORD
