Metadata-Version: 2.1
Name: terminalprint
Version: 0.0.5
Summary: a package for terminal pretty print
Home-page: https://github.com/xsddz/py_pkg_terminalprint
Author: xsddz
Author-email: dingzhns@gmail.com
License: MIT
Keywords: terminal print pretty table
Platform: UNKNOWN
Classifier: Development Status :: 3 - Alpha
Classifier: Intended Audience :: Developers
Classifier: Topic :: Software Development :: Build Tools
Classifier: License :: OSI Approved :: MIT License
Classifier: Programming Language :: Python :: 3
Requires-Python: >=3
